{
  "baseline": {
    "train_summary": {
      "n_rebalances": 146,
      "n_predictions": 6873,
      "date_start": "2017-05-19",
      "date_end": "2026-01-14",
      "oos_ic_spearman": 0.02429848693909745,
      "oos_cs_ic_mean": 0.040734301401086054,
      "oos_cs_ic_median": 0.03883076000242777,
      "oos_cs_ic_std": 0.19355223391551377,
      "oos_cs_ic_ir": 0.21045637437006653,
      "oos_cs_ic_positive_rate": 0.5958904109589042,
      "oos_top_bottom_mean": 0.011379538457149055,
      "oos_top_bottom_median": 0.011950770021526353,
      "oos_top_bottom_positive_rate": 0.6301369863013698,
      "oos_top_bottom_tstat": 2.823169257666285,
      "avg_validation_ic_spearman": 0.03990151139752551,
      "validation_scheme": "time_series_purged",
      "model_params": {
        "n_estimators": 500,
        "max_depth": 4,
        "learning_rate": 0.03,
        "subsample": 0.75,
        "colsample_bytree": 0.75,
        "objective": "reg:squarederror",
        "random_state": 42
      },
      "features": [
        "ret_1d",
        "ret_2d",
        "ret_5d",
        "ret_10d",
        "ret_20d",
        "ret_63d",
        "vol_5d",
        "vol_20d",
        "vol_60d",
        "vol_ratio_20_60",
        "downside_vol_20d",
        "upside_vol_20d",
        "momentum_20_60",
        "momentum_5_20",
        "momentum_x_vol_20",
        "reversal_1_5",
        "overnight_gap_1d",
        "intraday_return_1d",
        "high_low_range_1d",
        "dollar_volume_log_20d",
        "dollar_volume_z_60d",
        "mkt_nasdaq_proxy_lag1",
        "mkt_growth_proxy_lag1"
      ],
      "target_column": "fwd_return_15d_resid",
      "rebalance_frequency": "every_n_days",
      "rebalance_every_n_days": 15,
      "train_window_days": 756,
      "validation_window_days": 252,
      "horizon_days": 15,
      "training_target_transform": "cross_sectional_rank"
    },
    "backtest_summary": {
      "start_date": "2017-05-22",
      "end_date": "2026-02-20",
      "n_days": 2200,
      "n_rebalances": 146,
      "total_return": 19.037659941418354,
      "annualized_return": 0.40968038432350995,
      "annualized_volatility": 0.31013271788935326,
      "sharpe_ratio": 1.3209840842064027,
      "weekly_sharpe_ratio": 1.3669818564642031,
      "max_drawdown": -0.36646536653672834,
      "average_turnover": 0.24721089752691836,
      "total_cost_bps_paid": 252.64953727251057,
      "average_gross_exposure": 0.9018686794295392,
      "average_net_exposure": 0.9018686794295392,
      "portfolio_mode": "long_only",
      "allocation_method": "mean_variance",
      "signal_rank_zscore": true,
      "beta_neutralization_enabled": false,
      "signal_quality_gate_enabled": true,
      "average_overlay_leverage": 1.0,
      "min_overlay_leverage": 1.0,
      "max_overlay_leverage": 1.0,
      "risk_overlay_enabled": false,
      "average_signal_gate_multiplier": 0.9376712328767122,
      "min_signal_gate_multiplier": 0.35,
      "signal_gate_active_rate": 0.0958904109589041
    },
    "score": 3.3151162337923346
  },
  "recommended": {
    "train_summary": {
      "n_rebalances": 219,
      "n_predictions": 10316,
      "date_start": "2017-05-26",
      "date_end": "2026-01-29",
      "oos_ic_spearman": 0.038041188504554034,
      "oos_cs_ic_mean": 0.05329034857637368,
      "oos_cs_ic_median": 0.055003600175811344,
      "oos_cs_ic_std": 0.1932681851169117,
      "oos_cs_ic_ir": 0.2757326486205544,
      "oos_cs_ic_positive_rate": 0.6255707762557078,
      "oos_top_bottom_mean": 0.010224155779576872,
      "oos_top_bottom_median": 0.012008785409959852,
      "oos_top_bottom_positive_rate": 0.5707762557077626,
      "oos_top_bottom_tstat": 2.987340065778911,
      "avg_validation_ic_spearman": 0.04082295729551559,
      "validation_scheme": "time_series_purged",
      "model_params": {
        "n_estimators": 500,
        "max_depth": 4,
        "learning_rate": 0.03,
        "subsample": 0.75,
        "colsample_bytree": 0.75,
        "objective": "reg:squarederror",
        "random_state": 42
      },
      "features": [
        "ret_1d",
        "ret_2d",
        "ret_5d",
        "ret_10d",
        "ret_20d",
        "ret_63d",
        "vol_5d",
        "vol_20d",
        "vol_60d",
        "vol_ratio_20_60",
        "downside_vol_20d",
        "upside_vol_20d",
        "momentum_20_60",
        "momentum_5_20",
        "momentum_x_vol_20",
        "reversal_1_5",
        "overnight_gap_1d",
        "intraday_return_1d",
        "high_low_range_1d",
        "dollar_volume_log_20d",
        "dollar_volume_z_60d",
        "mkt_nasdaq_proxy_lag1",
        "mkt_growth_proxy_lag1"
      ],
      "target_column": "fwd_return_15d_resid",
      "rebalance_frequency": "every_n_days",
      "rebalance_every_n_days": 10,
      "train_window_days": 756,
      "validation_window_days": 252,
      "horizon_days": 15,
      "training_target_transform": "cross_sectional_rank"
    },
    "backtest_summary": {
      "start_date": "2017-05-30",
      "end_date": "2026-02-20",
      "n_days": 2195,
      "n_rebalances": 219,
      "total_return": 23.66558990375759,
      "annualized_return": 0.4448440835158636,
      "annualized_volatility": 0.3247708547261754,
      "sharpe_ratio": 1.3697167619641415,
      "weekly_sharpe_ratio": 1.4499376471718377,
      "max_drawdown": -0.37534636933732335,
      "average_turnover": 0.2929566462919347,
      "total_cost_bps_paid": 449.10253876553617,
      "average_gross_exposure": 0.9490635305765917,
      "average_net_exposure": 0.9490635305765917,
      "portfolio_mode": "long_only",
      "allocation_method": "mean_variance",
      "signal_rank_zscore": true,
      "beta_neutralization_enabled": false,
      "signal_quality_gate_enabled": true,
      "average_overlay_leverage": 1.0,
      "min_overlay_leverage": 1.0,
      "max_overlay_leverage": 1.0,
      "risk_overlay_enabled": false,
      "average_signal_gate_multiplier": 0.9579908675799086,
      "min_signal_gate_multiplier": 0.6,
      "signal_gate_active_rate": 0.1050228310502283
    },
    "score": 3.5439485631887937
  },
  "delta": {
    "annualized_return": 0.035163699192353626,
    "sharpe_ratio": 0.04873267775773882,
    "max_drawdown": -0.008881002800595006,
    "oos_cs_ic_mean": 0.012556047175287625,
    "oos_top_bottom_mean": -0.0011553826775721823,
    "score": 0.22883232939645914
  },
  "best_model_preset": {
    "n_estimators": 500,
    "max_depth": 4,
    "learning_rate": 0.03,
    "subsample": 0.75,
    "colsample_bytree": 0.75
  },
  "best_structural": {
    "rebalance_days": 10,
    "weight_max": 0.2,
    "turnover_cap": 0.3,
    "risk_aversion_lambda": 15.0,
    "overlay_enabled": false
  },
  "best_gate": {
    "threshold": 0.0,
    "bad_state_multiplier": 0.6,
    "lookback_rebalances": 20,
    "min_history_rebalances": 6
  },
  "artifacts": {
    "recommended_model": "/Users/jenriquezafra/Proyectos/Dev/python/portfolio/outputs/experiments/alpha_v2_tuning_auto/config_model.alpha_v2.tuned.yaml",
    "recommended_backtest": "/Users/jenriquezafra/Proyectos/Dev/python/portfolio/outputs/experiments/alpha_v2_tuning_auto/config_backtest.alpha_v2.tuned.yaml",
    "recommended_execution": "/Users/jenriquezafra/Proyectos/Dev/python/portfolio/outputs/experiments/alpha_v2_tuning_auto/config_execution.alpha_v2.tuned.yaml"
  }
}