{
  "ex_ante": {
    "max_abs": {
      "growth_proxy": 0.15204446712800418,
      "nasdaq_proxy": 0.2725904489244826
    },
    "mean": {
      "growth_proxy": 0.008037065937945091,
      "nasdaq_proxy": 0.008116969616898293
    }
  },
  "ex_post": {
    "by_year": [
      {
        "alpha_daily": 8.215205664842977e-05,
        "betas": {
          "growth_proxy": 0.08537839421814632,
          "nasdaq_proxy": -0.011483735937062898
        },
        "n_obs": 178,
        "r2": 0.0221801713308043,
        "year": 2017
      },
      {
        "alpha_daily": 0.00012041814394908645,
        "betas": {
          "growth_proxy": 0.04847024123409939,
          "nasdaq_proxy": 0.038669970923513104
        },
        "n_obs": 251,
        "r2": 0.030695317296321356,
        "year": 2018
      },
      {
        "alpha_daily": 0.00016908344895715397,
        "betas": {
          "growth_proxy": 0.10399524142385952,
          "nasdaq_proxy": 0.07785501462864858
        },
        "n_obs": 252,
        "r2": 0.09134347499840478,
        "year": 2019
      },
      {
        "alpha_daily": 0.00026627752769592833,
        "betas": {
          "growth_proxy": 0.0498416365234322,
          "nasdaq_proxy": 0.0001149465831461877
        },
        "n_obs": 253,
        "r2": 0.021283831908554762,
        "year": 2020
      },
      {
        "alpha_daily": -0.00020575820285008496,
        "betas": {
          "growth_proxy": 0.022530828155860577,
          "nasdaq_proxy": 0.12463268437528822
        },
        "n_obs": 252,
        "r2": 0.17980476636347176,
        "year": 2021
      },
      {
        "alpha_daily": -8.169015316804281e-05,
        "betas": {
          "growth_proxy": 0.03526784131999191,
          "nasdaq_proxy": -0.03391535814562753
        },
        "n_obs": 251,
        "r2": 0.01994340419597418,
        "year": 2022
      },
      {
        "alpha_daily": -6.698022664079713e-05,
        "betas": {
          "growth_proxy": 0.11768139803097655,
          "nasdaq_proxy": -0.13067671014838808
        },
        "n_obs": 250,
        "r2": 0.09133471561225459,
        "year": 2023
      },
      {
        "alpha_daily": -0.00028554517748273825,
        "betas": {
          "growth_proxy": -0.04643825513251003,
          "nasdaq_proxy": 0.03037692256737533
        },
        "n_obs": 252,
        "r2": 0.008404043818021734,
        "year": 2024
      },
      {
        "alpha_daily": -0.00010715019981727719,
        "betas": {
          "growth_proxy": -0.009926684184134756,
          "nasdaq_proxy": -0.004377416491315865
        },
        "n_obs": 250,
        "r2": 0.002185173956286257,
        "year": 2025
      },
      {
        "alpha_daily": -0.0006068121810630578,
        "betas": {
          "growth_proxy": 0.0067816792553691925,
          "nasdaq_proxy": -0.1824739160676296
        },
        "n_obs": 34,
        "r2": 0.19790771946085306,
        "year": 2026
      }
    ],
    "full_sample": {
      "alpha_daily": -5.302173525342384e-06,
      "betas": {
        "growth_proxy": 0.03296598560951304,
        "nasdaq_proxy": 0.0004230598568271973
      },
      "n_obs": 2223,
      "r2": 0.006060021777245739
    }
  },
  "factor_names": [
    "nasdaq_proxy",
    "growth_proxy"
  ]
}