{
  "ex_ante": {
    "max_abs": {
      "growth_proxy": 0.2820672034505223,
      "nasdaq_proxy": 0.4282108449033106
    },
    "mean": {
      "growth_proxy": -0.02494268881805335,
      "nasdaq_proxy": 0.05328572849121444
    }
  },
  "ex_post": {
    "by_year": [
      {
        "alpha_daily": 7.7917562162084e-06,
        "betas": {
          "growth_proxy": -0.04813828172358902,
          "nasdaq_proxy": 0.01646214474921252
        },
        "n_obs": 177,
        "r2": 0.017745988969639526,
        "year": 2017
      },
      {
        "alpha_daily": -1.0393881092444632e-05,
        "betas": {
          "growth_proxy": 0.05366535180468387,
          "nasdaq_proxy": 0.0867415930174504
        },
        "n_obs": 251,
        "r2": 0.2889328560063106,
        "year": 2018
      },
      {
        "alpha_daily": 7.3745660447641065e-06,
        "betas": {
          "growth_proxy": 0.001248356203493037,
          "nasdaq_proxy": 0.0548083252424912
        },
        "n_obs": 252,
        "r2": 0.11351400966431524,
        "year": 2019
      },
      {
        "alpha_daily": 7.883019383314341e-05,
        "betas": {
          "growth_proxy": -0.02474604027529136,
          "nasdaq_proxy": 0.016856799285267794
        },
        "n_obs": 253,
        "r2": 0.05026709895098158,
        "year": 2020
      },
      {
        "alpha_daily": 0.0001507546002762561,
        "betas": {
          "growth_proxy": -0.037261213623487534,
          "nasdaq_proxy": 0.06374768455307218
        },
        "n_obs": 252,
        "r2": 0.07334932129599403,
        "year": 2021
      },
      {
        "alpha_daily": 5.19750590459033e-05,
        "betas": {
          "growth_proxy": -0.05315531568915637,
          "nasdaq_proxy": 0.07773271526212305
        },
        "n_obs": 251,
        "r2": 0.24205085249428915,
        "year": 2022
      },
      {
        "alpha_daily": 0.0001237793755397159,
        "betas": {
          "growth_proxy": -0.04172385498524997,
          "nasdaq_proxy": 0.07196535610314592
        },
        "n_obs": 250,
        "r2": 0.07788642301128479,
        "year": 2023
      },
      {
        "alpha_daily": 0.00019891092727979072,
        "betas": {
          "growth_proxy": -0.03200953837327718,
          "nasdaq_proxy": 0.038206307458493384
        },
        "n_obs": 252,
        "r2": 0.023524467343058908,
        "year": 2024
      },
      {
        "alpha_daily": 0.00011783604503281794,
        "betas": {
          "growth_proxy": 0.011627951024886984,
          "nasdaq_proxy": 0.03459642639805891
        },
        "n_obs": 250,
        "r2": 0.06748657793113866,
        "year": 2025
      },
      {
        "alpha_daily": -0.0014351548598900182,
        "betas": {
          "growth_proxy": -0.015135738959631693,
          "nasdaq_proxy": 0.06524465656221273
        },
        "n_obs": 34,
        "r2": 0.02731363578220125,
        "year": 2026
      }
    ],
    "full_sample": {
      "alpha_daily": 5.2438336763083655e-05,
      "betas": {
        "growth_proxy": -0.01444900308574472,
        "nasdaq_proxy": 0.04836467373308365
      },
      "n_obs": 2222,
      "r2": 0.08873757645319358
    }
  },
  "factor_names": [
    "nasdaq_proxy",
    "growth_proxy"
  ]
}