{
  "ex_ante": {
    "max_abs": {
      "growth_proxy": 0.937613929706518,
      "nasdaq_proxy": 1.3659940633133156
    },
    "mean": {
      "growth_proxy": 0.0018604221981086328,
      "nasdaq_proxy": 0.016897388667808915
    }
  },
  "ex_post": {
    "by_year": [
      {
        "alpha_daily": 0.0011945258060902725,
        "betas": {
          "growth_proxy": 0.29501805376597745,
          "nasdaq_proxy": -0.03930297826745842
        },
        "n_obs": 178,
        "r2": 0.023585122866456754,
        "year": 2017
      },
      {
        "alpha_daily": -0.0006541863983356916,
        "betas": {
          "growth_proxy": 0.3070289872266863,
          "nasdaq_proxy": -0.12059682989361961
        },
        "n_obs": 251,
        "r2": 0.013388343319774565,
        "year": 2018
      },
      {
        "alpha_daily": 0.0004713823593090521,
        "betas": {
          "growth_proxy": 0.34165718948819623,
          "nasdaq_proxy": 0.1329107049814857
        },
        "n_obs": 252,
        "r2": 0.08080147701166851,
        "year": 2019
      },
      {
        "alpha_daily": 0.00038661115779036625,
        "betas": {
          "growth_proxy": -0.0396355701862414,
          "nasdaq_proxy": 0.053353382211148236
        },
        "n_obs": 253,
        "r2": 0.01591579167542545,
        "year": 2020
      },
      {
        "alpha_daily": -0.00050025834887195,
        "betas": {
          "growth_proxy": -0.03529005291876869,
          "nasdaq_proxy": 0.2532942936693029
        },
        "n_obs": 252,
        "r2": 0.07371596417138926,
        "year": 2021
      },
      {
        "alpha_daily": 3.9678419034547745e-05,
        "betas": {
          "growth_proxy": 0.19350715212111655,
          "nasdaq_proxy": -0.08339723058270644
        },
        "n_obs": 251,
        "r2": 0.016479635265049697,
        "year": 2022
      },
      {
        "alpha_daily": 0.0007771654105321538,
        "betas": {
          "growth_proxy": 0.16354208675399573,
          "nasdaq_proxy": -0.23947383495816127
        },
        "n_obs": 250,
        "r2": 0.052715202502875314,
        "year": 2023
      },
      {
        "alpha_daily": -0.0008488374189517154,
        "betas": {
          "growth_proxy": 0.07323287000264073,
          "nasdaq_proxy": -0.08300911934535297
        },
        "n_obs": 252,
        "r2": 0.0036803367319095948,
        "year": 2024
      },
      {
        "alpha_daily": -0.00014647041683688827,
        "betas": {
          "growth_proxy": -0.08911086907874985,
          "nasdaq_proxy": -0.011912513808255335
        },
        "n_obs": 250,
        "r2": 0.00766040278950697,
        "year": 2025
      },
      {
        "alpha_daily": -0.0007257020179305046,
        "betas": {
          "growth_proxy": 0.41534496985212094,
          "nasdaq_proxy": -0.32385833555237675
        },
        "n_obs": 34,
        "r2": 0.09026077356157458,
        "year": 2026
      }
    ],
    "full_sample": {
      "alpha_daily": 3.491947199824654e-05,
      "betas": {
        "growth_proxy": 0.03536149492863281,
        "nasdaq_proxy": 0.006174341873795916
      },
      "n_obs": 2223,
      "r2": 0.0013638870228359634
    }
  },
  "factor_names": [
    "nasdaq_proxy",
    "growth_proxy"
  ]
}