{
  "ic_by_year": [
    {
      "ic_ir": 0.2934804205509964,
      "ic_mean": 0.07618242539215943,
      "ic_median": 0.12173095562542052,
      "ic_positive_rate": 0.6923076923076923,
      "ic_std": 0.259582650348975,
      "n_rebalances": 26,
      "year": 2017
    },
    {
      "ic_ir": 0.22694244627798282,
      "ic_mean": 0.052801648975799705,
      "ic_median": 0.004751292543132324,
      "ic_positive_rate": 0.5,
      "ic_std": 0.23266537327760506,
      "n_rebalances": 36,
      "year": 2018
    },
    {
      "ic_ir": 0.13833971560592423,
      "ic_mean": 0.033485371162425934,
      "ic_median": 0.0012472961248890953,
      "ic_positive_rate": 0.5,
      "ic_std": 0.242051756545551,
      "n_rebalances": 36,
      "year": 2019
    },
    {
      "ic_ir": -0.0011186089465996093,
      "ic_mean": -0.00030440564658873616,
      "ic_median": -0.03161149551091456,
      "ic_positive_rate": 0.4857142857142857,
      "ic_std": 0.2721287430375738,
      "n_rebalances": 35,
      "year": 2020
    },
    {
      "ic_ir": 0.004306453181481557,
      "ic_mean": 0.0010888789818044257,
      "ic_median": -0.005318332327704766,
      "ic_positive_rate": 0.5,
      "ic_std": 0.2528482107936946,
      "n_rebalances": 32,
      "year": 2021
    },
    {
      "ic_ir": -0.18941093395565398,
      "ic_mean": -0.05277187813061135,
      "ic_median": -0.04057242151965149,
      "ic_positive_rate": 0.4411764705882353,
      "ic_std": 0.2786105164497347,
      "n_rebalances": 34,
      "year": 2022
    },
    {
      "ic_ir": 0.15635573498439403,
      "ic_mean": 0.05689829707014291,
      "ic_median": 0.047316792565987066,
      "ic_positive_rate": 0.5714285714285714,
      "ic_std": 0.36390284677323775,
      "n_rebalances": 35,
      "year": 2023
    },
    {
      "ic_ir": 0.10704887414102905,
      "ic_mean": 0.028061184219188004,
      "ic_median": 0.03193210580101806,
      "ic_positive_rate": 0.5555555555555556,
      "ic_std": 0.2621343236381865,
      "n_rebalances": 36,
      "year": 2024
    },
    {
      "ic_ir": 0.2185244711409495,
      "ic_mean": 0.06917481637305256,
      "ic_median": 0.08853955982661876,
      "ic_positive_rate": 0.5833333333333334,
      "ic_std": 0.31655409580391763,
      "n_rebalances": 36,
      "year": 2025
    },
    {
      "ic_ir": -0.5293281303321394,
      "ic_mean": -0.12089126239808455,
      "ic_median": -0.10346153846153845,
      "ic_positive_rate": 0.25,
      "ic_std": 0.22838624186141113,
      "n_rebalances": 4,
      "year": 2026
    }
  ],
  "returns_by_year": [
    {
      "annualized_return": -0.0008177584385997694,
      "annualized_volatility": 0.014499404037029026,
      "n_days": 177,
      "sharpe_ratio": -0.05639945176445546,
      "total_return": -0.0005744478718490154,
      "year": 2017
    },
    {
      "annualized_return": 0.005740892924408936,
      "annualized_volatility": 0.03189571421027777,
      "n_days": 251,
      "sharpe_ratio": 0.17998947716176378,
      "total_return": 0.005718046594988646,
      "year": 2018
    },
    {
      "annualized_return": 0.009762502300509457,
      "annualized_volatility": 0.023525865379617924,
      "n_days": 252,
      "sharpe_ratio": 0.41496889245006835,
      "total_return": 0.009762502300509457,
      "year": 2019
    },
    {
      "annualized_return": 0.01644704356934734,
      "annualized_volatility": 0.026361883753204803,
      "n_days": 253,
      "sharpe_ratio": 0.623894852254171,
      "total_return": 0.016512845543328325,
      "year": 2020
    },
    {
      "annualized_return": 0.03338697413177849,
      "annualized_volatility": 0.025244169274724334,
      "n_days": 252,
      "sharpe_ratio": 1.3225618069835683,
      "total_return": 0.03338697413177849,
      "year": 2021
    },
    {
      "annualized_return": -0.004601628683274295,
      "annualized_volatility": 0.033898160635980334,
      "n_days": 251,
      "sharpe_ratio": -0.1357486246138681,
      "total_return": -0.004583410163723989,
      "year": 2022
    },
    {
      "annualized_return": 0.04532515979128493,
      "annualized_volatility": 0.03244083713153935,
      "n_days": 250,
      "sharpe_ratio": 1.3971636924011217,
      "total_return": 0.04495746917077659,
      "year": 2023
    },
    {
      "annualized_return": 0.035711903833726355,
      "annualized_volatility": 0.025221285275585047,
      "n_days": 252,
      "sharpe_ratio": 1.415943059345058,
      "total_return": 0.035711903833726355,
      "year": 2024
    },
    {
      "annualized_return": 0.031323487725396726,
      "annualized_volatility": 0.03126017858882971,
      "n_days": 250,
      "sharpe_ratio": 1.0020252327217876,
      "total_return": 0.031071066044335405,
      "year": 2025
    },
    {
      "annualized_return": -0.2524412273797,
      "annualized_volatility": 0.04486106194943574,
      "n_days": 34,
      "sharpe_ratio": -5.627179037006171,
      "total_return": -0.03849366638617968,
      "year": 2026
    }
  ],
  "returns_three_blocks": [
    {
      "annualized_return": 0.00436583726953832,
      "annualized_volatility": 0.026164852609928478,
      "block": 1,
      "end_date": "2020-03-30",
      "n_days": 741,
      "sharpe_ratio": 0.16685885201133008,
      "start_date": "2017-04-20"
    },
    {
      "annualized_return": 0.021992112832379673,
      "annualized_volatility": 0.028001332155696196,
      "block": 2,
      "end_date": "2023-03-09",
      "n_days": 741,
      "sharpe_ratio": 0.7853952344158708,
      "start_date": "2020-03-31"
    },
    {
      "annualized_return": 0.018247579297064442,
      "annualized_volatility": 0.03103551955423895,
      "block": 3,
      "end_date": "2026-02-20",
      "n_days": 740,
      "sharpe_ratio": 0.5879579127126975,
      "start_date": "2023-03-10"
    }
  ]
}